start_sdk/__init__.py
start_sdk/cf_img.py
start_sdk/cf_r2.py
start_sdk/github.py
start_sdk-0.0.22.dist-info/WHEEL
start_sdk-0.0.22.dist-info/METADATA
start_sdk-0.0.22.dist-info/RECORD
