Metadata-Version: 2.1
Name: start-sdk
Version: 0.0.22
Summary: Settings for Github, Cloudflare Images API
Home-page: https://mv3.dev
License: MIT
Author: Marcelino G. Veloso III
Author-email: mars@veloso.one
Requires-Python: >=3.10,<4.0
Classifier: Development Status :: 4 - Beta
Classifier: Framework :: Pytest
Classifier: License :: OSI Approved :: MIT License
Classifier: Programming Language :: Python :: 3
Classifier: Programming Language :: Python :: 3.10
Classifier: Programming Language :: Python :: 3.11
Classifier: Programming Language :: Python :: 3.11
Classifier: Typing :: Typed
Requires-Dist: boto3 (>=1.26,<2.0)
Requires-Dist: httpx (>=0.23.3,<0.24.0)
Requires-Dist: loguru (>=0.6.0,<0.7.0)
Requires-Dist: pydantic (>=1.10.6,<2.0.0)
Requires-Dist: python-dotenv (>=1.0,<2.0)
Requires-Dist: pyyaml (>=6.0,<7.0)
Project-URL: Documentation, https://mv3.dev/start-sdk
Project-URL: Repository, https://github.com/justmars/start-sdk
